pvorca/LICENSE
pvorca/__init__.py
pvorca/_factory.py
pvorca/_orca.py
pvorca/_util.py
pvorca/lib/common/orca_params_en_female.pv
pvorca/lib/linux/x86_64/libpv_orca.so
pvorca/lib/mac/arm64/libpv_orca.dylib
pvorca/lib/mac/x86_64/libpv_orca.dylib
pvorca/lib/raspberry-pi/cortex-a53/libpv_orca.so
pvorca/lib/raspberry-pi/cortex-a53-aarch64/libpv_orca.so
pvorca/lib/raspberry-pi/cortex-a72/libpv_orca.so
pvorca/lib/raspberry-pi/cortex-a72-aarch64/libpv_orca.so
pvorca/lib/raspberry-pi/cortex-a76/libpv_orca.so
pvorca/lib/raspberry-pi/cortex-a76-aarch64/libpv_orca.so
pvorca/lib/windows/amd64/libpv_orca.dll
pvorca/lib/windows/amd64/pv_ypu_impl_cuda.dll
pvorca/lib/windows/arm64/libpv_orca.dll
pvorca-2.0.0.dist-info/METADATA
pvorca-2.0.0.dist-info/WHEEL
pvorca-2.0.0.dist-info/top_level.txt
pvorca-2.0.0.dist-info/RECORD
