Metadata-Version: 2.4
Name: pvorca
Version: 2.0.0
Summary: Orca Streaming Text-to-Speech Engine
Home-page: https://github.com/Picovoice/orca
Author: Picovoice
Author-email: hello@picovoice.ai
Keywords: Streaming Text-to-Speech,TTS,Speech Synthesis,Voice Generation,Speech Engine
Classifier: Development Status :: 5 - Production/Stable
Classifier: Intended Audience :: Developers
Classifier: License :: OSI Approved :: Apache Software License
Classifier: Operating System :: OS Independent
Classifier: Programming Language :: Python :: 3
Classifier: Topic :: Multimedia :: Sound/Audio :: Speech
Requires-Python: >=3.9
Dynamic: author
Dynamic: author-email
Dynamic: classifier
Dynamic: description
Dynamic: description-content-type
Dynamic: home-page
Dynamic: keywords
Dynamic: requires-python
Dynamic: summary
